boxyboi/__init__.py
boxyboi/box.py
boxyboi-2.2.3.dist-info/METADATA
boxyboi-2.2.3.dist-info/RECORD
boxyboi-2.2.3.dist-info/WHEEL
boxyboi-2.2.3.dist-info/top_level.txt
